{
  "source_mesh": "/home/htaucare/Tesis_Amaro/data/Teeth_3ds/raw/data_part_2/upper/SL5I9AXM/SL5I9AXM_upper.obj",
  "source_json": "/home/htaucare/Tesis_Amaro/data/Teeth_3ds/raw/data_part_2/upper/SL5I9AXM/SL5I9AXM_upper.json",
  "n_points": 200000,
  "mode": "SURF_SAMPLE_GLOBAL",
  "sample_mode": "global",
  "label_policy": "exclude_wisdom_to_0",
  "label_policy_stats": {
    "n_total": 200000,
    "n_to_0_wisdom": 0,
    "n_to_0_other": 0
  },
  "labels_unique_after_policy": {
    "0": 114505,
    "11": 7141,
    "12": 4960,
    "13": 5358,
    "14": 5540,
    "15": 4786,
    "16": 8927,
    "17": 5702,
    "21": 7038,
    "22": 4409,
    "23": 5533,
    "24": 6189,
    "25": 5262,
    "26": 8837,
    "27": 5813
  }
}