{
  "source_mesh": "/home/htaucare/Tesis_Amaro/data/Teeth_3ds/raw/data_part_3/lower/3HRLKQ4M/3HRLKQ4M_lower.obj",
  "source_json": "/home/htaucare/Tesis_Amaro/data/Teeth_3ds/raw/data_part_3/lower/3HRLKQ4M/3HRLKQ4M_lower.json",
  "n_points": 200000,
  "mode": "SURF_SAMPLE_GLOBAL",
  "sample_mode": "global",
  "label_policy": "exclude_wisdom_to_0",
  "label_policy_stats": {
    "n_total": 200000,
    "n_to_0_wisdom": 0,
    "n_to_0_other": 0
  },
  "labels_unique_after_policy": {
    "0": 161315,
    "31": 1905,
    "32": 2183,
    "33": 2770,
    "34": 2620,
    "35": 2554,
    "36": 4548,
    "37": 2794,
    "41": 1918,
    "42": 2258,
    "43": 2536,
    "44": 2507,
    "45": 2460,
    "46": 4715,
    "47": 2917
  }
}