{
  "source_mesh": "/home/htaucare/Tesis_Amaro/data/Teeth_3ds/raw/data_part_4/upper/01K17AN8/01K17AN8_upper.obj",
  "source_json": "/home/htaucare/Tesis_Amaro/data/Teeth_3ds/raw/data_part_4/upper/01K17AN8/01K17AN8_upper.json",
  "n_points": 200000,
  "mode": "SURF_SAMPLE_GLOBAL",
  "sample_mode": "global",
  "label_policy": "exclude_wisdom_to_0",
  "label_policy_stats": {
    "n_total": 200000,
    "n_to_0_wisdom": 0,
    "n_to_0_other": 0
  },
  "labels_unique_after_policy": {
    "0": 167548,
    "11": 2699,
    "12": 1729,
    "13": 1473,
    "14": 2186,
    "15": 2030,
    "16": 3942,
    "17": 2477,
    "21": 2806,
    "22": 1798,
    "23": 1490,
    "24": 2258,
    "25": 2079,
    "26": 3526,
    "27": 1959
  }
}