{
  "source_mesh": "/home/htaucare/Tesis_Amaro/data/Teeth_3ds/raw/data_part_5/upper/6TZ254SP/6TZ254SP_upper.obj",
  "source_json": "/home/htaucare/Tesis_Amaro/data/Teeth_3ds/raw/data_part_5/upper/6TZ254SP/6TZ254SP_upper.json",
  "n_points": 200000,
  "mode": "SURF_SAMPLE_GLOBAL",
  "sample_mode": "global",
  "label_policy": "exclude_wisdom_to_0",
  "label_policy_stats": {
    "n_total": 200000,
    "n_to_0_wisdom": 0,
    "n_to_0_other": 0
  },
  "labels_unique_after_policy": {
    "0": 168925,
    "11": 2266,
    "12": 1367,
    "13": 1663,
    "14": 1649,
    "15": 1948,
    "16": 3639,
    "17": 2903,
    "21": 2198,
    "22": 1521,
    "23": 1540,
    "24": 1776,
    "25": 2005,
    "26": 3738,
    "27": 2862
  }
}