{
  "source_mesh": "/home/htaucare/Tesis_Amaro/data/Teeth_3ds/raw/data_part_1/lower/Q5GSR6N2/Q5GSR6N2_lower.obj",
  "source_json": "/home/htaucare/Tesis_Amaro/data/Teeth_3ds/raw/data_part_1/lower/Q5GSR6N2/Q5GSR6N2_lower.json",
  "n_points": 200000,
  "mode": "SURF_SAMPLE_GLOBAL",
  "sample_mode": "global",
  "label_policy": "exclude_wisdom_to_0",
  "label_policy_stats": {
    "n_total": 200000,
    "n_to_0_wisdom": 0,
    "n_to_0_other": 0
  },
  "labels_unique_after_policy": {
    "0": 144475,
    "31": 3217,
    "32": 3579,
    "33": 3395,
    "34": 3647,
    "35": 4118,
    "36": 6519,
    "37": 4364,
    "41": 3244,
    "42": 3625,
    "43": 4099,
    "44": 3903,
    "45": 3962,
    "46": 7853
  }
}