{
  "source_mesh": "/home/htaucare/Tesis_Amaro/data/Teeth_3ds/raw/data_part_3/upper/014M2HZD/014M2HZD_upper.obj",
  "source_json": "/home/htaucare/Tesis_Amaro/data/Teeth_3ds/raw/data_part_3/upper/014M2HZD/014M2HZD_upper.json",
  "n_points": 200000,
  "mode": "SURF_SAMPLE_GLOBAL",
  "sample_mode": "global",
  "label_policy": "exclude_wisdom_to_0",
  "label_policy_stats": {
    "n_total": 200000,
    "n_to_0_wisdom": 0,
    "n_to_0_other": 0
  },
  "labels_unique_after_policy": {
    "0": 157887,
    "11": 3039,
    "12": 2190,
    "13": 2985,
    "14": 2709,
    "15": 2335,
    "16": 4102,
    "17": 3434,
    "21": 3183,
    "22": 2251,
    "23": 3114,
    "24": 2719,
    "25": 2225,
    "26": 4182,
    "27": 3645
  }
}